{
  "citations": [
    {
      "paperId": "d0ce7b3642a4da9f10ee592cbf7237a768d1f5e7",
      "title": "Characteristic and functional study of intersex, a gene involved in sexual development in Gryllus bimaculatus.",
      "year": 2025,
      "citationCount": 0,
      "authors": [
        {
          "authorId": "2345931377",
          "name": "Jia-Xin Duan"
        },
        {
          "authorId": "2345892364",
          "name": "Li-Dong Shi"
        },
        {
          "authorId": "2115834329",
          "name": "Yun Bai"
        },
        {
          "authorId": "2238787958",
          "name": "Mi Di"
        },
        {
          "authorId": "2310264801",
          "name": "Ning Zhang"
        },
        {
          "authorId": "2345886424",
          "name": "Gang-Qi Fang"
        },
        {
          "authorId": "2338526574",
          "name": "Dong-Liang Li"
        },
        {
          "authorId": "2345897963",
          "name": "Zhu-Qing He"
        },
        {
          "authorId": "2158258758",
          "name": "Kai Li"
        }
      ]
    },
    {
      "paperId": "a9b28ffaea86000371a4308fc99555e52c2dff43",
      "title": "Understanding the genetics of sex determination in insects and its relevance to genetic pest management.",
      "year": 2024,
      "citationCount": 0,
      "authors": [
        {
          "authorId": "2338052297",
          "name": "Jade S Ashmore"
        },
        {
          "authorId": "4614989",
          "name": "B. Slippers"
        },
        {
          "authorId": "2244155728",
          "name": "Tuan A. Duong"
        },
        {
          "authorId": "1422759200",
          "name": "G. Dittrich‐Schröder"
        }
      ]
    },
    {
      "paperId": "ccbd035e585812794f42ed672645fb5b21a77044",
      "title": "Sex-specific mRNA alternative splicing patterns and Dmrt1 isoforms contribute to sex determination and differentiation of oyster.",
      "year": 2024,
      "citationCount": 0,
      "authors": [
        {
          "authorId": "2331272550",
          "name": "Lang Guo"
        },
        {
          "authorId": "2292023924",
          "name": "Hong Yu"
        },
        {
          "authorId": "2146240522",
          "name": "Qi Li"
        }
      ]
    },
    {
      "paperId": "bc52f7ab0d3a043b8bbf81010efeb8cec218970a",
      "title": "Male is the default sex: functional significance of the sex determination cascade in horned dung beetles",
      "year": 2024,
      "citationCount": 0,
      "authors": [
        {
          "authorId": "2325945732",
          "name": "London C. Mitchell"
        },
        {
          "authorId": "2198196135",
          "name": "Armin P. Moczek"
        },
        {
          "authorId": "2214135208",
          "name": "Erica M. Nadolski"
        }
      ]
    },
    {
      "paperId": "d0022625e7effa8017e33d0359696c981883657c",
      "title": "Transcriptomic analysis of sexually dimorphic cypris larvae of the rhizocephalan barnacle Peltogasterella gracilis.",
      "year": 2024,
      "citationCount": 0,
      "authors": [
        {
          "authorId": "2197452100",
          "name": "Asami Kajimoto"
        },
        {
          "authorId": "2096824490",
          "name": "Kenji Toyota"
        },
        {
          "authorId": "2256513876",
          "name": "Tsuyoshi Ohira"
        },
        {
          "authorId": "2326374112",
          "name": "Yoichi Yusa"
        }
      ]
    },
    {
      "paperId": "df9f8bbf4498d7725bebecfcc3aa98260759a3da",
      "title": "Tissue-specific metabolomic signatures for a doublesex model of reduced sexual dimorphism",
      "year": 2024,
      "citationCount": 0,
      "authors": [
        {
          "authorId": "2321720119",
          "name": "Rene Coig"
        },
        {
          "authorId": "1670801188",
          "name": "Benjamin R. Harrison"
        },
        {
          "authorId": "2288727401",
          "name": "Richard S. Johnson"
        },
        {
          "authorId": "2260799248",
          "name": "M. MacCoss"
        },
        {
          "authorId": "2260556528",
          "name": "D. Promislow"
        }
      ]
    },
    {
      "paperId": "429c60b56db24e1046aa68d9a79d97750987bc8e",
      "title": "Cellular sex throughout the organism underlies somatic sexual differentiation",
      "year": 2024,
      "citationCount": 0,
      "authors": [
        {
          "authorId": "2261381907",
          "name": "Chloé Hérault"
        },
        {
          "authorId": "50723933",
          "name": "Thomas Pihl"
        },
        {
          "authorId": "2261381375",
          "name": "Bruno Hudry"
        }
      ]
    },
    {
      "paperId": "1a8f7c1b3c0f1d054c54e1072376bd529ba0dc1a",
      "title": "Evolution of the sex-determination gene Doublesex within the termite lineage",
      "year": 2024,
      "citationCount": 0,
      "authors": [
        {
          "authorId": "2106684530",
          "name": "Kokuto Fujiwara"
        },
        {
          "authorId": "2285469608",
          "name": "Satoshi Miyazaki"
        },
        {
          "authorId": "2285474656",
          "name": "K. Maekawa"
        }
      ]
    },
    {
      "paperId": "d14cfc9fc2e29e41163d498dd8f0930da1b98bd5",
      "title": "The role of fruitless in specifying courtship behaviors across divergent Drosophila species",
      "year": 2024,
      "citationCount": 0,
      "authors": [
        {
          "authorId": "2237998704",
          "name": "Christa A. Baker"
        },
        {
          "authorId": "2237999924",
          "name": "Xiao-Juan Guan"
        },
        {
          "authorId": "2291205925",
          "name": "Minseung Choi"
        },
        {
          "authorId": "145776127",
          "name": "Mala Murthy"
        }
      ]
    },
    {
      "paperId": "f07b9f1e34bbb4bf877d2dc34ee5b87d60040078",
      "title": "The Roles of transformer-2 (tra-2) in the Sex Determination and Fertility of Riptortus pedestris, a Hemimetabolous Agricultural Pest",
      "year": 2023,
      "citationCount": 0,
      "authors": [
        {
          "authorId": "2261596094",
          "name": "Jinjun Ying"
        },
        {
          "authorId": "2261668606",
          "name": "Haiqiang Wang"
        },
        {
          "authorId": "2261570801",
          "name": "Biyun Wang"
        },
        {
          "authorId": "2261726754",
          "name": "Zeping Mao"
        },
        {
          "authorId": "2261802016",
          "name": "Youyuan Chen"
        },
        {
          "authorId": "46275602",
          "name": "Junmin Li"
        },
        {
          "authorId": "2124556685",
          "name": "C. Zhang"
        },
        {
          "authorId": "2261592138",
          "name": "Jichong Zhuo"
        }
      ]
    },
    {
      "paperId": "3fe1f20c546c64ea03f6092ef014b933184d31d5",
      "title": "Spenito-dependent metabolic sexual dimorphism intrinsic to fat storage cells.",
      "year": 2023,
      "citationCount": 2,
      "authors": [
        {
          "authorId": "1384151177",
          "name": "Arely V Diaz"
        },
        {
          "authorId": "2239490276",
          "name": "D. Stephenson"
        },
        {
          "authorId": "5285327",
          "name": "T. Nemkov"
        },
        {
          "authorId": "2239206415",
          "name": "Angelo D’Alessandro"
        },
        {
          "authorId": "31187024",
          "name": "Tânia Reis"
        }
      ]
    },
    {
      "paperId": "27bb22b344d80002e5eb296541b7bdff63ec592a",
      "title": "The role of fruitless in specifying courtship behaviors differs across Drosophila species",
      "year": 2023,
      "citationCount": 1,
      "authors": [
        {
          "authorId": "2237998704",
          "name": "Christa A. Baker"
        },
        {
          "authorId": "2237999924",
          "name": "Xiao-Juan Guan"
        },
        {
          "authorId": "20070003",
          "name": "Minseung Choi"
        },
        {
          "authorId": "145776127",
          "name": "Mala Murthy"
        }
      ]
    },
    {
      "paperId": "76381d6131435e3630871b712929d6a12edafe7b",
      "title": "Transformer gene regulates feminization under two complementary sex determination loci in the ant, Vollenhovia emeryi.",
      "year": 2023,
      "citationCount": 1,
      "authors": [
        {
          "authorId": "4027065",
          "name": "M. O. Miyakawa"
        },
        {
          "authorId": "4555093",
          "name": "H. Miyakawa"
        }
      ]
    },
    {
      "paperId": "ee769f47958e678e9b0229c8c07683ad8a11984d",
      "title": "Expression and functional analysis of transformer-2 in Phytoseiulus persimilis and other genes potentially participating in reproductive regulation",
      "year": 2023,
      "citationCount": 1,
      "authors": [
        {
          "authorId": "89291833",
          "name": "Q. Cai"
        },
        {
          "authorId": "1421836985",
          "name": "Zhenghui Wang"
        },
        {
          "authorId": "2152891407",
          "name": "Fan Yang"
        },
        {
          "authorId": "2156622751",
          "name": "Bo Zhang"
        },
        {
          "authorId": "48663928",
          "name": "En-dong Wang"
        },
        {
          "authorId": "4211206",
          "name": "J. Lv"
        },
        {
          "authorId": "7925625",
          "name": "Xuenong Xu"
        }
      ]
    },
    {
      "paperId": "329e55f7c8dd11b3c51acdfcf1d9b9475544b209",
      "title": "In Vitro Comparison of Sex-Specific Splicing Efficiencies of fem Pre-mRNA under Monoallelic and Heteroallelic Conditions of csd, a Master Sex-Determining Gene in the Honeybee",
      "year": 2023,
      "citationCount": 1,
      "authors": [
        {
          "authorId": "2218417556",
          "name": "Yukihiro Suzuki"
        },
        {
          "authorId": "2211246490",
          "name": "Takafumi Yamada"
        },
        {
          "authorId": "2111452760",
          "name": "Masataka G Suzuki"
        }
      ]
    },
    {
      "paperId": "f8d7adb351f9d9bcb0e35827cb2ddf354f30d8ac",
      "title": "Maleness-on-the-Y (MoY) orthologue is a key regulator of male sex determination in Zeugodacus cucurbitae (Diptera: Tephritidae)",
      "year": 2022,
      "citationCount": 5,
      "authors": [
        {
          "authorId": "2180699128",
          "name": "Zi-zhen Fan"
        },
        {
          "authorId": "2117132445",
          "name": "Qin Ma"
        },
        {
          "authorId": "90321600",
          "name": "Siwecka Ma"
        },
        {
          "authorId": "2084767147",
          "name": "Feng-qin Cao"
        },
        {
          "authorId": "2180679008",
          "name": "Ri-hui Yan"
        },
        {
          "authorId": "2117691056",
          "name": "Xianwu Lin"
        }
      ]
    },
    {
      "paperId": "1e7276afd86b91a6eaf7b3927b0444131fe234ed",
      "title": "DMRT Transcription Factors in the Control of Nervous System Sexual Differentiation",
      "year": 2022,
      "citationCount": 5,
      "authors": [
        {
          "authorId": "1446683821",
          "name": "Rafael Casado-Navarro"
        },
        {
          "authorId": "1399030076",
          "name": "Esther Serrano-Saiz"
        }
      ]
    },
    {
      "paperId": "127a6d0ac06bb16b32159bd5f7edd16db9c5407a",
      "title": "Alternative splicing as a source of phenotypic diversity",
      "year": 2022,
      "citationCount": 183,
      "authors": [
        {
          "authorId": "2058030993",
          "name": "Charlotte J. Wright"
        },
        {
          "authorId": "2116353872",
          "name": "Christopher W. J. Smith"
        },
        {
          "authorId": "3178465",
          "name": "C. Jiggins"
        }
      ]
    },
    {
      "paperId": "59ade0c389c460c594781a04d7394ec26ae52fa2",
      "title": "Manipulating Insect Sex Determination Pathways for Genetic Pest Management: Opportunities and Challenges",
      "year": 2022,
      "citationCount": 13,
      "authors": [
        {
          "authorId": "120840854",
          "name": "A. Siddall"
        },
        {
          "authorId": "1412673861",
          "name": "T. Harvey‐Samuel"
        },
        {
          "authorId": "144118867",
          "name": "T. Chapman"
        },
        {
          "authorId": "4096793",
          "name": "P. Leftwich"
        }
      ]
    },
    {
      "paperId": "f43241a91e594aad6acfa54480319db39f1e060c",
      "title": "The AalNix3&4 isoform is required and sufficient to convert Aedes albopictus females into males",
      "year": 2022,
      "citationCount": 4,
      "authors": [
        {
          "authorId": "3419411",
          "name": "Yijie Zhao"
        },
        {
          "authorId": "50203419",
          "name": "Binbin Jin"
        },
        {
          "authorId": "5068788",
          "name": "Peiwen Liu"
        },
        {
          "authorId": "2172382422",
          "name": "Xiaolin Xiao"
        },
        {
          "authorId": "2112829999",
          "name": "Lijun Cai"
        },
        {
          "authorId": "5055210",
          "name": "Zhensheng Xie"
        },
        {
          "authorId": "1741825",
          "name": "Ling Kong"
        },
        {
          "authorId": "46999342",
          "name": "Tong Liu"
        },
        {
          "authorId": "50741045",
          "name": "Wenqiang Yang"
        },
        {
          "authorId": "2149122350",
          "name": "Yang Wu"
        },
        {
          "authorId": "4774319",
          "name": "J. Gu"
        },
        {
          "authorId": "2148987697",
          "name": "Z. Tu"
        },
        {
          "authorId": "2787983",
          "name": "A. James"
        },
        {
          "authorId": "2145272137",
          "name": "Xiao-Guang Chen"
        }
      ]
    },
    {
      "paperId": "841e1110e7523ba53f9a51a6142f817b2f452bcb",
      "title": "Transcriptome analysis of sex-biased gene expression in the spotted-wing Drosophila, Drosophila suzukii (Matsumura)",
      "year": 2022,
      "citationCount": 8,
      "authors": [
        {
          "authorId": "2165776874",
          "name": "Dan Deng"
        },
        {
          "authorId": "2165776453",
          "name": "Shisi Xing"
        },
        {
          "authorId": "1491679658",
          "name": "Xuxiang Liu"
        },
        {
          "authorId": "40831917",
          "name": "Q. Ji"
        },
        {
          "authorId": "3778475",
          "name": "Zongzhao Zhai"
        },
        {
          "authorId": "49161536",
          "name": "Wei Peng"
        }
      ]
    },
    {
      "paperId": "b76689d7a94a56c334e9abd42526fe2a4833bb63",
      "title": "Sex-specific regulation of development, growth and metabolism.",
      "year": 2022,
      "citationCount": 12,
      "authors": [
        {
          "authorId": "1687452",
          "name": "A. Shingleton"
        },
        {
          "authorId": "6119521",
          "name": "I. Vea"
        }
      ]
    },
    {
      "paperId": "f1beb8bec65a370bdee1601d3609cec03b31eb98",
      "title": "Transcriptome analysis reveals differentially expressed genes between the ovary and testis of the honey bee Apis mellifera",
      "year": 2022,
      "citationCount": 1,
      "authors": [
        {
          "authorId": "2088258792",
          "name": "L. Pan"
        },
        {
          "authorId": "3491819",
          "name": "Wanqi Hu"
        },
        {
          "authorId": "2117596976",
          "name": "F.‐P. Cheng"
        },
        {
          "authorId": "2109582623",
          "name": "Xiao-Fen Hu"
        },
        {
          "authorId": "2274070985",
          "name": "Zi-Long Wang"
        }
      ]
    },
    {
      "paperId": "f17fbe28a533914467a6f38eeaae230a05f0a09c",
      "title": "Transcriptome characterization and expression analysis related to sex‐determining genes in Chilo sacchariphagus (Lepidoptera Crambidae), a key pest of sugarcane",
      "year": 2022,
      "citationCount": 1,
      "authors": [
        {
          "authorId": "51190270",
          "name": "Jianbai Liu"
        },
        {
          "authorId": "2118499529",
          "name": "Hangli Wu"
        },
        {
          "authorId": "40791610",
          "name": "Jiequn Yi"
        },
        {
          "authorId": "51090361",
          "name": "Jihu Li"
        },
        {
          "authorId": "49096734",
          "name": "Yin Cheng"
        },
        {
          "authorId": "2145062676",
          "name": "Yifei Zhang"
        },
        {
          "authorId": "14524809",
          "name": "Donglei Sun"
        },
        {
          "authorId": "39942601",
          "name": "Yuxing An"
        }
      ]
    },
    {
      "paperId": "7121b95c5acddac5479c7c7149925d819700de25",
      "title": "Doublesex regulates male-specific differentiation during distinct developmental time windows in a parasitoid wasp.",
      "year": 2022,
      "citationCount": 11,
      "authors": [
        {
          "authorId": "2130356168",
          "name": "Yidong Wang"
        },
        {
          "authorId": "117206940",
          "name": "Anna H. Rensink"
        },
        {
          "authorId": "2048195658",
          "name": "Ute Fricke"
        },
        {
          "authorId": "30028554",
          "name": "Megan C Riddle"
        },
        {
          "authorId": "7583836",
          "name": "C. Trent"
        },
        {
          "authorId": "120216765",
          "name": "L. van de Zande"
        },
        {
          "authorId": "32019767",
          "name": "E. Verhulst"
        }
      ]
    },
    {
      "paperId": "a504f1409213fbc35d362876893c9893b7d6ba1a",
      "title": "Identification and expression pattern of the sex determination gene fruitless-like in Cherax quadricarinatus.",
      "year": 2021,
      "citationCount": 3,
      "authors": [
        {
          "authorId": "2116442372",
          "name": "D. Lin"
        },
        {
          "authorId": "145251589",
          "name": "Yongjun Guo"
        },
        {
          "authorId": "2109243136",
          "name": "Xiuli Chen"
        },
        {
          "authorId": "13050657",
          "name": "Huizan Yang"
        },
        {
          "authorId": "122927235",
          "name": "Qiangyong Li"
        },
        {
          "authorId": "2112266796",
          "name": "Qingyun Liu"
        },
        {
          "authorId": "17866105",
          "name": "Fuli Luo"
        },
        {
          "authorId": "2145684872",
          "name": "Kui Meng"
        },
        {
          "authorId": "2152686403",
          "name": "Songting Yang"
        },
        {
          "authorId": "10689684",
          "name": "Xinquan Cheng"
        },
        {
          "authorId": "2152618313",
          "name": "Wenming Ma"
        },
        {
          "authorId": "2155475474",
          "name": "Xiaohan Chen"
        },
        {
          "authorId": "2148629498",
          "name": "Moran Wang"
        },
        {
          "authorId": "49339329",
          "name": "Yongzhen Zhao"
        }
      ]
    },
    {
      "paperId": "5a54e17998c2787dbe37c81f225cc5c586300477",
      "title": "A feminizing switch in a hemimetabolous insect",
      "year": 2021,
      "citationCount": 9,
      "authors": [
        {
          "authorId": "36438355",
          "name": "Ji-Chong Zhuo"
        },
        {
          "authorId": "89396470",
          "name": "Hou-Hong Zhang"
        },
        {
          "authorId": "2113362968",
          "name": "Qingqing Hu"
        },
        {
          "authorId": "2144199849",
          "name": "Jin-Li Zhang"
        },
        {
          "authorId": "2199947399",
          "name": "Jia-Bao Lu"
        },
        {
          "authorId": "2118385538",
          "name": "Han-Jing Li"
        },
        {
          "authorId": "2118596411",
          "name": "Yu-Cheng Xie"
        },
        {
          "authorId": "47825073",
          "name": "Wen Wang"
        },
        {
          "authorId": "2152819594",
          "name": "Yan Zhang"
        },
        {
          "authorId": "2109050359",
          "name": "Hai-Qiang Wang"
        },
        {
          "authorId": "4252956",
          "name": "Hai-Jian Huang"
        },
        {
          "authorId": "2087109594",
          "name": "Gang Lu"
        },
        {
          "authorId": "1455163556",
          "name": "Jian-ping Chen"
        },
        {
          "authorId": "46275602",
          "name": "Junmin Li"
        },
        {
          "authorId": "2909321",
          "name": "Zhaopeng Tu"
        },
        {
          "authorId": "2124556685",
          "name": "C. Zhang"
        }
      ]
    },
    {
      "paperId": "2c02d8aa148f6f46d5f2849687e1a5bc224ad113",
      "title": "Early embryonic transcriptomes of Zeugodacus tau provide insight into sex determination and differentiation genes",
      "year": 2021,
      "citationCount": 9,
      "authors": [
        {
          "authorId": "2129354283",
          "name": "Peipei Liu"
        },
        {
          "authorId": "2152935147",
          "name": "Wenping Zheng"
        },
        {
          "authorId": "2147351002",
          "name": "Jiao Qiao"
        },
        {
          "authorId": "2118274082",
          "name": "Ziniu Li"
        },
        {
          "authorId": "2152158760",
          "name": "Zhurong Deng"
        },
        {
          "authorId": "2112499702",
          "name": "Yimin Yuan"
        },
        {
          "authorId": "48212520",
          "name": "Hongyu Zhang"
        }
      ]
    },
    {
      "paperId": "d42c83bdbfa8322374893e2f1e1cb149dd9cf1af",
      "title": "Sex determination gene transformer regulates the male-female difference in Drosophila fat storage via the adipokinetic hormone pathway",
      "year": 2021,
      "citationCount": 22,
      "authors": [
        {
          "authorId": "1490726130",
          "name": "Lianna W. Wat"
        },
        {
          "authorId": "29482494",
          "name": "Z. S. Chowdhury"
        },
        {
          "authorId": "89651785",
          "name": "Jason W. Millington"
        },
        {
          "authorId": "1490726932",
          "name": "Puja Biswas"
        },
        {
          "authorId": "46853436",
          "name": "Elizabeth J. Rideout"
        }
      ]
    },
    {
      "paperId": "111dc67fc2db6454a25053f366e93c7028025764",
      "title": "Lessons from Drosophila: Engineering Genetic Sexing Strains with Temperature-Sensitive Lethality for Sterile Insect Technique Applications",
      "year": 2021,
      "citationCount": 15,
      "authors": [
        {
          "authorId": "134800671",
          "name": "Thu N. M. Nguyen"
        },
        {
          "authorId": "38843402",
          "name": "A. Choo"
        },
        {
          "authorId": "2004459",
          "name": "S. Baxter"
        }
      ]
    },
    {
      "paperId": "fe74be033564ff20e85f062910235863007a00e0",
      "title": "Female-biased upregulation of insulin pathway activity mediates the sex difference in Drosophila body size plasticity",
      "year": 2021,
      "citationCount": 32,
      "authors": [
        {
          "authorId": "89651785",
          "name": "Jason W. Millington"
        },
        {
          "authorId": "1677115668",
          "name": "George P. Brownrigg"
        },
        {
          "authorId": "2046864714",
          "name": "Charlotte F. Chao"
        },
        {
          "authorId": "1664747742",
          "name": "Ziwei Sun"
        },
        {
          "authorId": "1666210960",
          "name": "Paige J. Basner-Collins"
        },
        {
          "authorId": "1490726130",
          "name": "Lianna W. Wat"
        },
        {
          "authorId": "4984170",
          "name": "Bruno Hudry"
        },
        {
          "authorId": "1401113746",
          "name": "I. Miguel-Aliaga"
        },
        {
          "authorId": "46853436",
          "name": "Elizabeth J. Rideout"
        }
      ]
    },
    {
      "paperId": "b22f403bc6f6077028f5f0d58fee935535736712",
      "title": "Integrated mRNA and miRNA expression profile analysis of female and male gonads in Hyriopsis cumingii",
      "year": 2021,
      "citationCount": 14,
      "authors": [
        {
          "authorId": "2109266565",
          "name": "Yayu Wang"
        },
        {
          "authorId": "2098945495",
          "name": "Sheng-Hua Duan"
        },
        {
          "authorId": "1680699",
          "name": "Gui-Ling Wang"
        },
        {
          "authorId": "2108961035",
          "name": "Jia-Le Li"
        }
      ]
    },
    {
      "paperId": "48948a17ed651fffb3933d69f56fe4a3a947c08f",
      "title": "A chimeric gene paternally instructs female sex determination in the haplodiploid wasp Nasonia",
      "year": 2020,
      "citationCount": 35,
      "authors": [
        {
          "authorId": "2028894316",
          "name": "Yuan Zou"
        },
        {
          "authorId": "6761704",
          "name": "E. Geuverink"
        },
        {
          "authorId": "4796443",
          "name": "L. Beukeboom"
        },
        {
          "authorId": "32019767",
          "name": "E. Verhulst"
        },
        {
          "authorId": "120216765",
          "name": "L. van de Zande"
        }
      ]
    },
    {
      "paperId": "d6d19e57e45983863970514b2a8b993449512b4e",
      "title": "Opposite Roles of Tra2β and SRSF9 in the v10 Exon Splicing of CD44",
      "year": 2020,
      "citationCount": 10,
      "authors": [
        {
          "authorId": "23560697",
          "name": "Jagyeong Oh"
        },
        {
          "authorId": "49420265",
          "name": "Yongchao Liu"
        },
        {
          "authorId": "38603792",
          "name": "Namjeong Choi"
        },
        {
          "authorId": "50773855",
          "name": "Jiyeon Ha"
        },
        {
          "authorId": "5825667",
          "name": "D. Pradella"
        },
        {
          "authorId": "6525173",
          "name": "C. Ghigna"
        },
        {
          "authorId": "6388250",
          "name": "Xuexiu Zheng"
        },
        {
          "authorId": "38738522",
          "name": "Hai-hong Shen"
        }
      ]
    },
    {
      "paperId": "440d0a0136e5364a21d07b79d3359853f4260099",
      "title": "Transgenic and knockout analyses of Masculinizer and doublesex illuminated the unique functions of doublesex in germ cell sexual development of the silkworm, Bombyx mori",
      "year": 2020,
      "citationCount": 10,
      "authors": [
        {
          "authorId": "90287240",
          "name": "Tomohisa Yuzawa"
        },
        {
          "authorId": "2059636304",
          "name": "M. Matsuoka"
        },
        {
          "authorId": "14999346",
          "name": "M. Sumitani"
        },
        {
          "authorId": "39906774",
          "name": "F. Aoki"
        },
        {
          "authorId": "2633743",
          "name": "H. Sezutsu"
        },
        {
          "authorId": "2111452760",
          "name": "Masataka G Suzuki"
        }
      ]
    },
    {
      "paperId": "4e02f211c47c164ff916364f412ffb674e077042",
      "title": "An Evaluation of Differentially Spliced Genes as Markers of Sex for Forensic Entomology , ,",
      "year": 2020,
      "citationCount": 8,
      "authors": [
        {
          "authorId": "84244551",
          "name": "Michelle M. Jonika"
        },
        {
          "authorId": "5499058",
          "name": "Carl E. Hjelmen"
        },
        {
          "authorId": "47221311",
          "name": "A. Faris"
        },
        {
          "authorId": "1506992651",
          "name": "A. S. McGuane"
        },
        {
          "authorId": "2898755",
          "name": "A. Tarone"
        }
      ]
    },
    {
      "paperId": "9ddd88b1d938a6c6529d6182be4adc7fe2acdcde",
      "title": "Transcriptome Analysis of the Oriental Fruit Fly Bactrocera dorsalis Early Embryos",
      "year": 2020,
      "citationCount": 3,
      "authors": [
        {
          "authorId": "2067859948",
          "name": "W. Peng"
        },
        {
          "authorId": "50443277",
          "name": "Shuning Yu"
        },
        {
          "authorId": "5332056",
          "name": "A. Handler"
        },
        {
          "authorId": "48212520",
          "name": "Hongyu Zhang"
        }
      ]
    },
    {
      "paperId": "b23c617adef19a2c045965c4ce29aa574e9317ee",
      "title": "Female-specific upregulation of insulin pathway activity mediates the sex difference in Drosophila body size plasticity",
      "year": 2020,
      "citationCount": 4,
      "authors": [
        {
          "authorId": "89651785",
          "name": "Jason W. Millington"
        },
        {
          "authorId": "2056250674",
          "name": "Chien Chao"
        },
        {
          "authorId": "1664747742",
          "name": "Ziwei Sun"
        },
        {
          "authorId": "1666210960",
          "name": "Paige J. Basner-Collins"
        },
        {
          "authorId": "1677115668",
          "name": "George P. Brownrigg"
        },
        {
          "authorId": "1490726130",
          "name": "Lianna W. Wat"
        },
        {
          "authorId": "4984170",
          "name": "Bruno Hudry"
        },
        {
          "authorId": "1401113746",
          "name": "I. Miguel-Aliaga"
        },
        {
          "authorId": "46853436",
          "name": "Elizabeth J. Rideout"
        }
      ]
    },
    {
      "paperId": "d61fbeb8b3849928cdec6724a5ba103c95788e2b",
      "title": "Male-Biased Adult Production of the Striped Fruit Fly, Zeugodacus scutellata, by Feeding dsRNA Specific to Transformer-2",
      "year": 2020,
      "citationCount": 5,
      "authors": [
        {
          "authorId": "134348107",
          "name": "Md. Abdullah Al Baki"
        },
        {
          "authorId": "51198409",
          "name": "M. Vatanparast"
        },
        {
          "authorId": "144802390",
          "name": "Yonggyun Kim"
        }
      ]
    },
    {
      "paperId": "1869d90d2da49a18d6055499402ddfaffc993ccd",
      "title": "Identification of a female determinant gene for the sexual determination of a hemipteran insect, the brown planthopper",
      "year": 2019,
      "citationCount": 3,
      "authors": [
        {
          "authorId": "36438355",
          "name": "Ji-Chong Zhuo"
        },
        {
          "authorId": "89396470",
          "name": "Hou-Hong Zhang"
        },
        {
          "authorId": "2118596411",
          "name": "Yu-Cheng Xie"
        },
        {
          "authorId": "2118385538",
          "name": "Han-Jing Li"
        },
        {
          "authorId": "51307224",
          "name": "Q. Hu"
        },
        {
          "authorId": "3764324",
          "name": "Chuan-Xi Zhang"
        }
      ]
    },
    {
      "paperId": "1062cb4e9ea62d257a406c474bfc6cf05884cd16",
      "title": "An antisense lncRNA functions in alternative splicing of Bmdsx in the silkworm, Bombyx mori.",
      "year": 2019,
      "citationCount": 15,
      "authors": [
        {
          "authorId": "2145785752",
          "name": "Xiaomin Xu"
        },
        {
          "authorId": "32230373",
          "name": "Kaixuan Wang"
        },
        {
          "authorId": "39939287",
          "name": "X. Zha"
        }
      ]
    },
    {
      "paperId": "b8e66a3824898b97fa0f89ee2af32ca22de056d6",
      "title": "Identification of sex determination genes and their evolution in Phlebotominae sand flies (Diptera, Nematocera)",
      "year": 2019,
      "citationCount": 13,
      "authors": [
        {
          "authorId": "40222608",
          "name": "V. Petrella"
        },
        {
          "authorId": "5186732",
          "name": "S. Aceto"
        },
        {
          "authorId": "49281244",
          "name": "V. Colonna"
        },
        {
          "authorId": "40626757",
          "name": "G. Saccone"
        },
        {
          "authorId": "2865446",
          "name": "R. Sanges"
        },
        {
          "authorId": "47882326",
          "name": "N. Polanska"
        },
        {
          "authorId": "1777412",
          "name": "P. Volf"
        },
        {
          "authorId": "6239546",
          "name": "L. Gradoni"
        },
        {
          "authorId": "4173192",
          "name": "G. Bongiorno"
        },
        {
          "authorId": "2127051",
          "name": "M. Salvemini"
        }
      ]
    },
    {
      "paperId": "0fa5eb79dac668055598624535ea1bfaf3551e2f",
      "title": "Downregulation of female doublesex expression by oral-mediated RNA interference reduces number and fitness of Anopheles gambiae adult females",
      "year": 2019,
      "citationCount": 29,
      "authors": [
        {
          "authorId": "3632202",
          "name": "M. Taracena"
        },
        {
          "authorId": "49683326",
          "name": "Catherine M Hunt"
        },
        {
          "authorId": "2017661",
          "name": "M. Benedict"
        },
        {
          "authorId": "6298695",
          "name": "P. Pennington"
        },
        {
          "authorId": "8236058",
          "name": "E. Dotson"
        }
      ]
    },
    {
      "paperId": "1ad3c603e767259d76a5511a53067c520388ab3d",
      "title": "Precise staging of beetle horn formation in Trypoxylus dichotomus reveals the pleiotropic roles of doublesex depending on the spatiotemporal developmental contexts",
      "year": 2019,
      "citationCount": 30,
      "authors": [
        {
          "authorId": "49133558",
          "name": "S. Morita"
        },
        {
          "authorId": "8737256",
          "name": "Toshiya Ando"
        },
        {
          "authorId": "35424392",
          "name": "Akiteru Maeno"
        },
        {
          "authorId": "2053400876",
          "name": "Takeshi Mizutani"
        },
        {
          "authorId": "79675763",
          "name": "Mutsuki Mase"
        },
        {
          "authorId": "6554159",
          "name": "S. Shigenobu"
        },
        {
          "authorId": "34780197",
          "name": "T. Niimi"
        }
      ]
    },
    {
      "paperId": "3c1670cef12581d3596b7bb04ed06579579da06c",
      "title": "Isolation and expression analysis of a candidate gametophyte sex determination gene (sjhmg) of kelp (Saccharina japonica)",
      "year": 2019,
      "citationCount": 11,
      "authors": [
        {
          "authorId": "2108039567",
          "name": "Linan Zhang"
        },
        {
          "authorId": "2344185705",
          "name": "Jinku Li"
        },
        {
          "authorId": "2119797687",
          "name": "Hao Wu"
        },
        {
          "authorId": "2247959561",
          "name": "Yingxia Li"
        }
      ]
    },
    {
      "paperId": "9aeb6db2aa4e26cdd0251f09311cf069d2e2b6fa",
      "title": "Hemimetabolous insects elucidate the origin of sexual development via alternative splicing",
      "year": 2019,
      "citationCount": 56,
      "authors": [
        {
          "authorId": "27982846",
          "name": "Judith R. Wexler"
        },
        {
          "authorId": "152452995",
          "name": "Emily K Delaney"
        },
        {
          "authorId": "5552122",
          "name": "X. Belles"
        },
        {
          "authorId": "3903160",
          "name": "C. Schal"
        },
        {
          "authorId": "1399207831",
          "name": "Ayako Wada-Katsumata"
        },
        {
          "authorId": "30154041",
          "name": "Matthew J Amicucci"
        },
        {
          "authorId": "2261246",
          "name": "A. Kopp"
        }
      ]
    },
    {
      "paperId": "49274a5c3da79b5866546fbb25b8ef991965fe31",
      "title": "Cytogenetic evolution of genus Salmo",
      "year": 2019,
      "citationCount": 0,
      "authors": [
        {
          "authorId": "2145245142",
          "name": "Song Lin"
        }
      ]
    },
    {
      "paperId": "32c8fc1ca657346711b1c111ebc1e54fffa28ab7",
      "title": "HITS-CLIP reveals sex-differential RNA binding and alterative splicing regulation of SRm160 in Drosophila",
      "year": 2019,
      "citationCount": 4,
      "authors": [
        {
          "authorId": "4062465",
          "name": "C. Qiu"
        },
        {
          "authorId": "2153637954",
          "name": "Yu Zhang"
        },
        {
          "authorId": "6742885",
          "name": "Yu-Jie Fan"
        },
        {
          "authorId": "41073296",
          "name": "Ting-Lin Pang"
        },
        {
          "authorId": "48576805",
          "name": "Yan Su"
        },
        {
          "authorId": "12698664",
          "name": "Shuai Zhan"
        },
        {
          "authorId": "6936546",
          "name": "Yong-Zhen Xu"
        }
      ]
    },
    {
      "paperId": "2d16d77419ca2650911a44055a55a2b5b1efcf97",
      "title": "Genomics and transcriptomics to unravel sex determination pathway and its evolution in sand flies",
      "year": 2019,
      "citationCount": 1,
      "authors": [
        {
          "authorId": "40222608",
          "name": "V. Petrella"
        },
        {
          "authorId": "5186732",
          "name": "S. Aceto"
        },
        {
          "authorId": "49281244",
          "name": "V. Colonna"
        },
        {
          "authorId": "40626757",
          "name": "G. Saccone"
        },
        {
          "authorId": "2865446",
          "name": "R. Sanges"
        },
        {
          "authorId": "47882326",
          "name": "N. Polanska"
        },
        {
          "authorId": "1777412",
          "name": "P. Volf"
        },
        {
          "authorId": "6239546",
          "name": "L. Gradoni"
        },
        {
          "authorId": "4173192",
          "name": "G. Bongiorno"
        },
        {
          "authorId": "2127051",
          "name": "M. Salvemini"
        }
      ]
    },
    {
      "paperId": "07ec4ac93b0a218b85570f166afcd4a543129a3d",
      "title": "Sex differences in Drosophila development and physiology",
      "year": 2018,
      "citationCount": 47,
      "authors": [
        {
          "authorId": "89651785",
          "name": "Jason W. Millington"
        },
        {
          "authorId": "46853436",
          "name": "Elizabeth J. Rideout"
        }
      ]
    },
    {
      "paperId": "2710025f5fe9471abf194b2f35d199e4a916c908",
      "title": "The decapod researcher’s guide to the galaxy of sex determination",
      "year": 2018,
      "citationCount": 32,
      "authors": [
        {
          "authorId": "47208167",
          "name": "J. Chandler"
        },
        {
          "authorId": "34645285",
          "name": "A. Elizur"
        },
        {
          "authorId": "3769340",
          "name": "T. Ventura"
        }
      ]
    },
    {
      "paperId": "3ec21a42a09fbe5e54ca05ab60c3bc44909d7c53",
      "title": "Identification and functional analysis of the doublesex gene in the sexual development of a hemimetabolous insect, the brown planthopper.",
      "year": 2018,
      "citationCount": 43,
      "authors": [
        {
          "authorId": "36438355",
          "name": "Ji-Chong Zhuo"
        },
        {
          "authorId": "51307224",
          "name": "Q. Hu"
        },
        {
          "authorId": "89396470",
          "name": "Hou-Hong Zhang"
        },
        {
          "authorId": "25853640",
          "name": "Meng-Qiu Zhang"
        },
        {
          "authorId": "153058752",
          "name": "S. B. Jo"
        },
        {
          "authorId": "3764324",
          "name": "Chuan-Xi Zhang"
        }
      ]
    },
    {
      "paperId": "9eb9b99abfcae6414fddb41ba230116eb510bcfc",
      "title": "Identification and characterization of doublesex from the pumpkin fruit fly, Bactrocera tau (Diptera: Tephritidae)",
      "year": 2018,
      "citationCount": 3,
      "authors": [
        {
          "authorId": "5221141",
          "name": "Thanaset Thongsaiklaing"
        },
        {
          "authorId": "2288641486",
          "name": "H. Passara"
        },
        {
          "authorId": "91434406",
          "name": "Mingkwan Nipitwathanaphon"
        },
        {
          "authorId": "4218515",
          "name": "L. Ngernsiri"
        }
      ]
    },
    {
      "paperId": "f27bb6c66220240321768f0c040898a2e4259e24",
      "title": "Evidence for Stabilizing Selection Driving Mutational Turnover of Short Motifs in the Eukaryotic Complementary Sex Determiner (Csd) Protein",
      "year": 2018,
      "citationCount": 5,
      "authors": [
        {
          "authorId": "39370564",
          "name": "Vasco Koch"
        },
        {
          "authorId": "49495952",
          "name": "M. Otte"
        },
        {
          "authorId": "144084140",
          "name": "M. Beye"
        }
      ]
    },
    {
      "paperId": "797046b763a91c132f6db5c56dc6719d8fb665e5",
      "title": "Evidence for involvement of a transformer paralogue in sex determination of the wasp Leptopilina clavipes",
      "year": 2018,
      "citationCount": 12,
      "authors": [
        {
          "authorId": "6761704",
          "name": "E. Geuverink"
        },
        {
          "authorId": "2252268909",
          "name": "K. Kraaijeveld"
        },
        {
          "authorId": "2252268909",
          "name": "K. Kraaijeveld"
        },
        {
          "authorId": "20846299",
          "name": "M. V. Leussen"
        },
        {
          "authorId": "2208311167",
          "name": "F. Chen"
        },
        {
          "authorId": "49375020",
          "name": "J. Pijpe"
        },
        {
          "authorId": "6349927",
          "name": "M. Linskens"
        },
        {
          "authorId": "2241828155",
          "name": "Leo W. Beukeboom"
        },
        {
          "authorId": "7968705",
          "name": "L. Zande"
        }
      ]
    },
    {
      "paperId": "eef8dcfe1f0e699889aaab8cb09d44d13185cf1b",
      "title": "Monitoring food preference in Drosophila by oligonucleotide tagging",
      "year": 2018,
      "citationCount": 32,
      "authors": [
        {
          "authorId": "144834288",
          "name": "Annie Park"
        },
        {
          "authorId": "11554296",
          "name": "Tracy Tran"
        },
        {
          "authorId": "11063513",
          "name": "N. Atkinson"
        }
      ]
    },
    {
      "paperId": "3e32b6e582ac38b7aa806b16c4ff673b7241504a",
      "title": "The transformer2 gene of the pumpkin fruit fly, Bactrocera tau (Walker), functions in sex determination, male fertility and testis development",
      "year": 2018,
      "citationCount": 9,
      "authors": [
        {
          "authorId": "5221141",
          "name": "Thanaset Thongsaiklaing"
        },
        {
          "authorId": "7413259",
          "name": "Mingkwan Nipitwattanaphon"
        },
        {
          "authorId": "4218515",
          "name": "L. Ngernsiri"
        }
      ]
    },
    {
      "paperId": "edc5344f5a83fb75747dfe729a27566d44b87561",
      "title": "Conserved Domains in the Transformer Protein Act Complementary to Regulate Sex-Specific Splicing of Its Own Pre-mRNA",
      "year": 2018,
      "citationCount": 11,
      "authors": [
        {
          "authorId": "15792888",
          "name": "Arisa Tanaka"
        },
        {
          "authorId": "39906774",
          "name": "F. Aoki"
        },
        {
          "authorId": "2111452760",
          "name": "Masataka G Suzuki"
        }
      ]
    },
    {
      "paperId": "78d2120590015fd58a2b4ad21f3ce64dfc33fb23",
      "title": "doublesex regulates sexually dimorphic beetle horn formation by integrating spatial and temporal developmental contexts in the Japanese rhinoceros beetle Trypoxylus dichotomus",
      "year": 2018,
      "citationCount": 1,
      "authors": [
        {
          "authorId": "49133558",
          "name": "S. Morita"
        },
        {
          "authorId": "8737256",
          "name": "Toshiya Ando"
        },
        {
          "authorId": "35424392",
          "name": "Akiteru Maeno"
        },
        {
          "authorId": "2053400876",
          "name": "Takeshi Mizutani"
        },
        {
          "authorId": "79675763",
          "name": "Mutsuki Mase"
        },
        {
          "authorId": "6554159",
          "name": "S. Shigenobu"
        },
        {
          "authorId": "34780197",
          "name": "T. Niimi"
        }
      ]
    },
    {
      "paperId": "e1cc660253c0b1b6a8d9d9a2aa42c566f801bc66",
      "title": "Effect of parental RNA interference of a transformer‐2 homologue on female reproduction and offspring sex determination in Asian citrus psyllid",
      "year": 2018,
      "citationCount": 21,
      "authors": [
        {
          "authorId": "7932563",
          "name": "Xiudao Yu"
        },
        {
          "authorId": "6149997",
          "name": "N. Killiny"
        }
      ]
    },
    {
      "paperId": "a692d8bc103d44d4027155f58af0d484311fa069",
      "title": "Drosophila female-specific Ilp7 motoneurons are generated by Fruitless-dependent cell death in males and by a double-assurance survival role for Transformer in females",
      "year": 2018,
      "citationCount": 14,
      "authors": [
        {
          "authorId": "47168969",
          "name": "S. Garner"
        },
        {
          "authorId": "152344057",
          "name": "M. C. Castellanos"
        },
        {
          "authorId": "35628753",
          "name": "Katherine E Baillie"
        },
        {
          "authorId": "39038522",
          "name": "Tianshun Lian"
        },
        {
          "authorId": "31289533",
          "name": "D. Allan"
        }
      ]
    },
    {
      "paperId": "3c329bd6ef434a7f03674fec258d44df9f637be8",
      "title": "Sex determination and differentiation genes in a functional hermaphrodite scallop, Nodipecten subnodosus.",
      "year": 2017,
      "citationCount": 19,
      "authors": [
        {
          "authorId": "1440972608",
          "name": "Pavel Galindo-Torres"
        },
        {
          "authorId": "1395415943",
          "name": "A. García‐Gasca"
        },
        {
          "authorId": "1402995658",
          "name": "R. Llera‐Herrera"
        },
        {
          "authorId": "1399816614",
          "name": "C. Escobedo‐Fregoso"
        },
        {
          "authorId": "1405101052",
          "name": "C. Abreu-Goodger"
        },
        {
          "authorId": "22320163",
          "name": "A. Ibarra"
        }
      ]
    },
    {
      "paperId": "892c5003be598b9d9d03da40d43f82a896187978",
      "title": "Tra-2 Mediates Cross-Talk Between Sex Determination and Wing Polyphenism in Female Nilaparvata lugens",
      "year": 2017,
      "citationCount": 23,
      "authors": [
        {
          "authorId": "36438355",
          "name": "Ji-Chong Zhuo"
        },
        {
          "authorId": "2064399167",
          "name": "Chen Lei"
        },
        {
          "authorId": "25908831",
          "name": "Ji-Kai Shi"
        },
        {
          "authorId": "2072805490",
          "name": "N. Xu"
        },
        {
          "authorId": "48122659",
          "name": "W-H Xue"
        },
        {
          "authorId": "25853640",
          "name": "Meng-Qiu Zhang"
        },
        {
          "authorId": "25927759",
          "name": "Ze-Wei Ren"
        },
        {
          "authorId": "89396470",
          "name": "Hou-Hong Zhang"
        },
        {
          "authorId": "3764324",
          "name": "Chuan-Xi Zhang"
        }
      ]
    },
    {
      "paperId": "520890fa9cc33c2351f472b501ef97eae7231daf",
      "title": "Identification and functional characterization of the sex-determining gene doublesex in the sawfly, Athalia rosae (Hymenoptera: Tenthredinidae)",
      "year": 2017,
      "citationCount": 27,
      "authors": [
        {
          "authorId": "12149660",
          "name": "Shotaro Mine"
        },
        {
          "authorId": "14999346",
          "name": "M. Sumitani"
        },
        {
          "authorId": "39906774",
          "name": "F. Aoki"
        },
        {
          "authorId": "40665709",
          "name": "M. Hatakeyama"
        },
        {
          "authorId": "2111452760",
          "name": "Masataka G Suzuki"
        }
      ]
    },
    {
      "paperId": "810e1dd72f64bb9f0cf3bfd03b20a95e285cdee9",
      "title": "Two spliced isoforms of the sex-determination gene fruitless in the Chinese mitten crab Eriocheir sinensis.",
      "year": 2017,
      "citationCount": 13,
      "authors": [
        {
          "authorId": "2112727785",
          "name": "Peiyao Li"
        },
        {
          "authorId": "14772260",
          "name": "Yuan Liu"
        },
        {
          "authorId": "4641164",
          "name": "Danli Luo"
        },
        {
          "authorId": "5384754",
          "name": "Chengwen Song"
        },
        {
          "authorId": "38116479",
          "name": "Z. Cui"
        }
      ]
    },
    {
      "paperId": "becd52e88a12231910faff64115b749a5946cda7",
      "title": "RNA-Seq-based transcriptome and the reproduction-related genes for the aphid Schlechtendalia chinensis (Hemiptera, Aphididae).",
      "year": 2017,
      "citationCount": 6,
      "authors": [
        {
          "authorId": "2157759690",
          "name": "P. Liu"
        },
        {
          "authorId": "12107319",
          "name": "Z. X. Yang"
        },
        {
          "authorId": "46771975",
          "name": "X. M. Chen"
        },
        {
          "authorId": "2328109118",
          "name": "P. Yang"
        }
      ]
    },
    {
      "paperId": "111e0a957181a580c2f7bf77ddb0f4456e83b0b1",
      "title": "Isolation and Molecular Characterization of the Transformer Gene From Bactrocera cucurbitae (Diptera: Tephritidae)",
      "year": 2017,
      "citationCount": 10,
      "authors": [
        {
          "authorId": "49513570",
          "name": "Yaowu Luo"
        },
        {
          "authorId": "26585643",
          "name": "Santao Zhao"
        },
        {
          "authorId": "2130139433",
          "name": "Jiahui Li"
        },
        {
          "authorId": "48982336",
          "name": "Peizhen Li"
        },
        {
          "authorId": "145222256",
          "name": "Rihui Yan"
        }
      ]
    },
    {
      "paperId": "2620e353f16fef1dae6421012a80fdb327822ade",
      "title": "De Novo Transcriptome Assembly and Sex-Biased Gene Expression in the Cyclical Parthenogenetic Daphnia galeata",
      "year": 2016,
      "citationCount": 38,
      "authors": [
        {
          "authorId": "123013517",
          "name": "A. Huylmans"
        },
        {
          "authorId": "11419385",
          "name": "Alberto López Ezquerra"
        },
        {
          "authorId": "2269228",
          "name": "J. Parsch"
        },
        {
          "authorId": "50572106",
          "name": "Mathilde Cordellier"
        }
      ]
    },
    {
      "paperId": "236be2550c8ea18e3edaa9035784ee20d44556fd",
      "title": "Role of Bmznf-2, a Bombyx mori CCCH zinc finger gene, in masculinisation and differential splicing of Bmtra-2.",
      "year": 2016,
      "citationCount": 13,
      "authors": [
        {
          "authorId": "5731199",
          "name": "G. Gopinath"
        },
        {
          "authorId": "1946014",
          "name": "K. P. Arunkumar"
        },
        {
          "authorId": "34855637",
          "name": "K. Mita"
        },
        {
          "authorId": "144916274",
          "name": "J. Nagaraju"
        }
      ]
    },
    {
      "paperId": "61853f6f5395c8923fe20c106c720410af7bb5a5",
      "title": "The autoregulatory loop: A common mechanism of regulation of key sex determining genes in insects",
      "year": 2016,
      "citationCount": 22,
      "authors": [
        {
          "authorId": "4384723",
          "name": "Suresh Kumar Sawanth"
        },
        {
          "authorId": "5731199",
          "name": "G. Gopinath"
        },
        {
          "authorId": "6936815",
          "name": "N. Sambrani"
        },
        {
          "authorId": "1946014",
          "name": "K. P. Arunkumar"
        }
      ]
    },
    {
      "paperId": "80bb99b44e32bc4d697c8963ec6cd6df6b664db3",
      "title": "Molecular cloning of the sex-related gene PSI in Bemisia tabaci and its alternative splicing properties.",
      "year": 2016,
      "citationCount": 5,
      "authors": [
        {
          "authorId": "2140191943",
          "name": "Yating Liu"
        },
        {
          "authorId": "2228691",
          "name": "W. Xie"
        },
        {
          "authorId": "144996338",
          "name": "Xin Yang"
        },
        {
          "authorId": "49868505",
          "name": "Litao Guo"
        },
        {
          "authorId": "50695924",
          "name": "Shaoli Wang"
        },
        {
          "authorId": "34675235",
          "name": "Qing-jun Wu"
        },
        {
          "authorId": "2155450911",
          "name": "Zezhong Yang"
        },
        {
          "authorId": "5477839",
          "name": "X. Zhou"
        },
        {
          "authorId": "98049771",
          "name": "Youjun Zhang"
        }
      ]
    },
    {
      "paperId": "efbdb40bf559822d9577988d026528c373e100d9",
      "title": "Identification and Characterization of Y Chromosome and M Locus Genes in Anopheles and Aedes Mosquitoes Using the Chromosome Quotient Method",
      "year": 2016,
      "citationCount": 0,
      "authors": [
        {
          "authorId": "144957945",
          "name": "A. B. Hall"
        }
      ]
    },
    {
      "paperId": "1e6ff484cf5cc1c54305d180de4049ac2a7f9140",
      "title": "The study of the transformer gene from Bactrocera dorsalis and B. correcta with putative core promoter regions",
      "year": 2016,
      "citationCount": 12,
      "authors": [
        {
          "authorId": "5148894",
          "name": "Kamoltip Laohakieat"
        },
        {
          "authorId": "5592987",
          "name": "N. Aketarawong"
        },
        {
          "authorId": "6796474",
          "name": "Siriwan Isasawin"
        },
        {
          "authorId": "4794343",
          "name": "S. Thitamadee"
        },
        {
          "authorId": "6837302",
          "name": "S. Thanaphum"
        }
      ]
    },
    {
      "paperId": "d0f946c84e0664d2d2c397334011d33958830db9",
      "title": "Mechanisms of sex determination and transmission ratio distortion in Aedes aegypti",
      "year": 2016,
      "citationCount": 28,
      "authors": [
        {
          "authorId": "32008724",
          "name": "Kim Phuc Hoang"
        },
        {
          "authorId": "4761124",
          "name": "T. M. Teo"
        },
        {
          "authorId": "4465046",
          "name": "T. Hồ"
        },
        {
          "authorId": "144186686",
          "name": "Vinh S Le"
        }
      ]
    },
    {
      "paperId": "f91bd807f70edc62a9c93fa24207940fdefe2893",
      "title": "The Sex Determination Gene transformer Regulates Male-Female Differences in Drosophila Body Size",
      "year": 2015,
      "citationCount": 84,
      "authors": [
        {
          "authorId": "46853436",
          "name": "Elizabeth J. Rideout"
        },
        {
          "authorId": "5948800",
          "name": "Marcus S. Narsaiya"
        },
        {
          "authorId": "34944565",
          "name": "S. Grewal"
        }
      ]
    },
    {
      "paperId": "ef7fa26b84f0c95ed291c87e3edd27ee6778580b",
      "title": "An Unusual Role for doublesex in Sex Determination in the Dipteran Sciara",
      "year": 2015,
      "citationCount": 12,
      "authors": [
        {
          "authorId": "35443813",
          "name": "M. Ruiz"
        },
        {
          "authorId": "2070354259",
          "name": "Mercedes Alvarez"
        },
        {
          "authorId": "1400083381",
          "name": "J. Eirín-López"
        },
        {
          "authorId": "4235721",
          "name": "Francesca Sarno"
        },
        {
          "authorId": "35354685",
          "name": "L. Kremer"
        },
        {
          "authorId": "143968908",
          "name": "J. Barbero"
        },
        {
          "authorId": "143783697",
          "name": "L. Sánchez"
        }
      ]
    },
    {
      "paperId": "7a61dfe803febc1d08cb9a269961ca67df610caf",
      "title": "Intra-domain Cross-talk Regulates Serine-arginine Protein Kinase 1-dependent Phosphorylation and Splicing Function of Transformer 2β1*",
      "year": 2015,
      "citationCount": 9,
      "authors": [
        {
          "authorId": "1924073",
          "name": "Michael A. Jamros"
        },
        {
          "authorId": "4487216",
          "name": "Brandon E. Aubol"
        },
        {
          "authorId": "4135845",
          "name": "Malik M. Keshwani"
        },
        {
          "authorId": "4513618",
          "name": "Zhaiyi Zhang"
        },
        {
          "authorId": "145538359",
          "name": "S. Stamm"
        },
        {
          "authorId": "31839713",
          "name": "J. Adams"
        }
      ]
    },
    {
      "paperId": "cd9d837d989db1e6d96406c764951a2a2a1e8e3f",
      "title": "The Evolving Puzzle of Autosomal Versus Y-linked Male Determination in Musca domestica",
      "year": 2014,
      "citationCount": 48,
      "authors": [
        {
          "authorId": "33248468",
          "name": "R. Hamm"
        },
        {
          "authorId": "144905443",
          "name": "R. Meisel"
        },
        {
          "authorId": "14366805",
          "name": "J. G. Scott"
        }
      ]
    },
    {
      "paperId": "458b6060af899336fb16ad667880509f665bd4ae",
      "title": "RNAi-mediated knockdown of transformer-2 in the predatory mite Metaseiulus occidentalis via oral delivery of double-stranded RNA",
      "year": 2014,
      "citationCount": 18,
      "authors": [
        {
          "authorId": "46918308",
          "name": "A. Pomerantz"
        },
        {
          "authorId": "6718855",
          "name": "M. Hoy"
        }
      ]
    },
    {
      "paperId": "85125e93ca299657daa00ec169d842ae4b6e6e72",
      "title": "ESTRUCTURA Y FUNCIÓN DE LOS SISTEMAS MOLECULARES DE DETERMINACIÓN SEXUAL EN DÍPTEROS",
      "year": 2014,
      "citationCount": 0,
      "authors": [
        {
          "authorId": "87026316",
          "name": "Julia María Lesher Gordillo"
        },
        {
          "authorId": "2070171870",
          "name": "René Fernando Molina Martínez"
        },
        {
          "authorId": "144676617",
          "name": "R. Martínez"
        },
        {
          "authorId": "120972234",
          "name": "A. R. López"
        }
      ]
    },
    {
      "paperId": "937703458f961e03775e8f822a238b774c547a2b",
      "title": "Altering the sex determination pathway in Drosophila fat body modifies sex-specific stress responses.",
      "year": 2014,
      "citationCount": 11,
      "authors": [
        {
          "authorId": "4652546",
          "name": "K. J. Argue"
        },
        {
          "authorId": "5077853",
          "name": "W. Neckameyer"
        }
      ]
    },
    {
      "paperId": "0b20b17fe48da0b30fb4b264fe56640882c21573",
      "title": "Sex-lethal gene of the Chinese mitten crab Eriocheir sinensis: cDNA cloning, induction by eyestalk ablation, and expression of two splice variants in males and females",
      "year": 2014,
      "citationCount": 40,
      "authors": [
        {
          "authorId": "5987437",
          "name": "Huaishun Shen"
        },
        {
          "authorId": "6909944",
          "name": "Yacheng Hu"
        },
        {
          "authorId": "2148927346",
          "name": "Xin Zhou"
        }
      ]
    },
    {
      "paperId": "3a8946a464c3ea9295f3c7f360e864fb3476b266",
      "title": "Lepidopteran Sex Determination: A Cascade of Surprises",
      "year": 2014,
      "citationCount": 26,
      "authors": [
        {
          "authorId": "2239301018",
          "name": "Javaregowda Nagaraju"
        },
        {
          "authorId": "5731199",
          "name": "G. Gopinath"
        },
        {
          "authorId": "2255471410",
          "name": "Vandana Sharma"
        },
        {
          "authorId": "35088122",
          "name": "J. Shukla"
        }
      ]
    },
    {
      "paperId": "d6876a4d2bb41f6b3bc868388837d165c154c4f4",
      "title": "Sex Determination Mechanisms in the Calliphoridae (Blow Flies)",
      "year": 2013,
      "citationCount": 27,
      "authors": [
        {
          "authorId": "37265674",
          "name": "Maxwell J. Scott"
        },
        {
          "authorId": "46732736",
          "name": "Meaghan L Pimsler"
        },
        {
          "authorId": "2898755",
          "name": "A. Tarone"
        }
      ]
    },
    {
      "paperId": "a9896dd2c5d3a24d90834943d9ca2ad3ec3a02cd",
      "title": "The expression analysis of Sfrs10 and Celf4 during mouse retinal development.",
      "year": 2013,
      "citationCount": 5,
      "authors": [
        {
          "authorId": "38892760",
          "name": "Devi Krishna Priya Karunakaran"
        },
        {
          "authorId": "5728550",
          "name": "Sean Congdon"
        },
        {
          "authorId": "6272367",
          "name": "Thomas A Guerrette"
        },
        {
          "authorId": "3283506",
          "name": "A. R. Banday"
        },
        {
          "authorId": "32219322",
          "name": "Christopher Lemoine"
        },
        {
          "authorId": "40241227",
          "name": "Nisarg Chhaya"
        },
        {
          "authorId": "48665327",
          "name": "R. Kanadia"
        }
      ]
    },
    {
      "paperId": "3469bce7e4ff48194d6f3bdf7488b62343874aa8",
      "title": "Tribolium castaneum Transformer-2 regulates sex determination and development in both males and females.",
      "year": 2013,
      "citationCount": 44,
      "authors": [
        {
          "authorId": "35088122",
          "name": "J. Shukla"
        },
        {
          "authorId": "6969952",
          "name": "S. R. Palli"
        }
      ]
    },
    {
      "paperId": "7e75cadaf13541240505ab36f7152b9c4f69ba86",
      "title": "A Novel Function for Juvenile Hormone in Male Courtship Behavior of Drosophila melanogaster",
      "year": 2013,
      "citationCount": 0,
      "authors": [
        {
          "authorId": "5489184",
          "name": "T. Wijesekera"
        }
      ]
    },
    {
      "paperId": "514c68a1c567739e505845d703c24b02d96c3a48",
      "title": "Alternative splicing: functional diversity among voltage-gated calcium channels and behavioral consequences.",
      "year": 2013,
      "citationCount": 111,
      "authors": [
        {
          "authorId": "5096003",
          "name": "D. Lipscombe"
        },
        {
          "authorId": "49094371",
          "name": "A. Andrade"
        },
        {
          "authorId": "4230533",
          "name": "S. Allen"
        }
      ]
    },
    {
      "paperId": "5b1ddb7f537cc7ce244c553a9bfaed21f75d1676",
      "title": "A Transgenerational Endocrine Signaling Pathway in Crustacea",
      "year": 2013,
      "citationCount": 38,
      "authors": [
        {
          "authorId": "1707527",
          "name": "G. LeBlanc"
        },
        {
          "authorId": "2155514941",
          "name": "Ying H. Wang"
        },
        {
          "authorId": "31862167",
          "name": "Charisse N. Holmes"
        },
        {
          "authorId": "1813499",
          "name": "Gwijun Kwon"
        },
        {
          "authorId": "40052295",
          "name": "Elizabeth K. Medlock"
        }
      ]
    },
    {
      "paperId": "ad60f295eaf2bccd99dbe597bdc45978f8dd615c",
      "title": "Neuroblast pattern and identity in the Drosophila tail region and role of doublesex in the survival of sex-specific precursors",
      "year": 2013,
      "citationCount": 50,
      "authors": [
        {
          "authorId": "3670335",
          "name": "Oliver Birkholz"
        },
        {
          "authorId": "5699933",
          "name": "C. Rickert"
        },
        {
          "authorId": "48498610",
          "name": "C. Berger"
        },
        {
          "authorId": "4174444",
          "name": "R. Urbach"
        },
        {
          "authorId": "4156168",
          "name": "G. Technau"
        }
      ]
    },
    {
      "paperId": "155a3558ee69c23ec1ba9e2f9f481922c483fa5b",
      "title": "The Orthologue of the Fruitfly Sex Behaviour Gene Fruitless in the Mosquito Aedes aegypti: Evolution of Genomic Organisation and Alternative Splicing",
      "year": 2013,
      "citationCount": 49,
      "authors": [
        {
          "authorId": "2127051",
          "name": "M. Salvemini"
        },
        {
          "authorId": "1401126103",
          "name": "Rocco D'Amato"
        },
        {
          "authorId": "40222608",
          "name": "V. Petrella"
        },
        {
          "authorId": "5186732",
          "name": "S. Aceto"
        },
        {
          "authorId": "3660112",
          "name": "Derric D. Nimmo"
        },
        {
          "authorId": "49542742",
          "name": "Marco Neira"
        },
        {
          "authorId": "4160003",
          "name": "L. Alphey"
        },
        {
          "authorId": "48709152",
          "name": "L. C. Polito"
        },
        {
          "authorId": "40626757",
          "name": "G. Saccone"
        }
      ]
    },
    {
      "paperId": "d3158e0709051424333f348067fbd635c5ce28f1",
      "title": "Doublesex target genes in the red flour beetle, Tribolium castaneum",
      "year": 2012,
      "citationCount": 78,
      "authors": [
        {
          "authorId": "35088122",
          "name": "J. Shukla"
        },
        {
          "authorId": "6969952",
          "name": "S. R. Palli"
        }
      ]
    },
    {
      "paperId": "3184ce454def94270e929d804f0e3acae34c2e64",
      "title": "The Am-tra2 Gene Is an Essential Regulator of Female Splice Regulation at Two Levels of the Sex Determination Hierarchy of the Honeybee",
      "year": 2012,
      "citationCount": 70,
      "authors": [
        {
          "authorId": "39470101",
          "name": "Inga Nissen"
        },
        {
          "authorId": "13818913",
          "name": "Miriam Müller"
        },
        {
          "authorId": "144084140",
          "name": "M. Beye"
        }
      ]
    },
    {
      "paperId": "375ea4fba13b5f70951094239d86349a258c603e",
      "title": "Investigating the evolution of sex-specific phenotypes",
      "year": 2012,
      "citationCount": 0,
      "authors": [
        {
          "authorId": "5170179",
          "name": "Charles Mullon"
        }
      ]
    },
    {
      "paperId": "023594d170f0adba5c9d5dcba03f1e5bbf56cb29",
      "title": "Sex determination in beetles: Production of all male progeny by Parental RNAi knockdown of transformer",
      "year": 2012,
      "citationCount": 88,
      "authors": [
        {
          "authorId": "35088122",
          "name": "J. Shukla"
        },
        {
          "authorId": "6969952",
          "name": "S. R. Palli"
        }
      ]
    },
    {
      "paperId": "c5faaeb58ab6474fb06f8dc3055536a960f59252",
      "title": "How does Tra2β protein regulate tissue-specific RNA splicing?",
      "year": 2012,
      "citationCount": 18,
      "authors": [
        {
          "authorId": "144728936",
          "name": "D. Elliott"
        },
        {
          "authorId": "1587105807",
          "name": "Andrew Best"
        },
        {
          "authorId": "143678839",
          "name": "Caroline Dalgliesh"
        },
        {
          "authorId": "48259602",
          "name": "Ingrid Ehrmann"
        },
        {
          "authorId": "5978925",
          "name": "S. Grellscheid"
        }
      ]
    },
    {
      "paperId": "c003db8d11806fc459197463716130bb61803331",
      "title": "Sex Modifies Genetic Effects on Residual Variance in Urinary Calcium Excretion in Rat (Rattus norvegicus)",
      "year": 2012,
      "citationCount": 26,
      "authors": [
        {
          "authorId": "50278924",
          "name": "G. Perry"
        },
        {
          "authorId": "152380438",
          "name": "K. Nehrke"
        },
        {
          "authorId": "3601022",
          "name": "D. Bushinsky"
        },
        {
          "authorId": "2070296653",
          "name": "R. Reid"
        },
        {
          "authorId": "16205779",
          "name": "Krista L Lewandowski"
        },
        {
          "authorId": "34668852",
          "name": "P. Hueber"
        },
        {
          "authorId": "5886432",
          "name": "S. Scheinman"
        }
      ]
    },
    {
      "paperId": "c5465375be37655d194e12daa6e830a0150c74e8",
      "title": "Sex-specific expression during embryonic development of Anopheles gambiae",
      "year": 2012,
      "citationCount": 0,
      "authors": [
        {
          "authorId": "35174104",
          "name": "Nathan J. Dennison"
        }
      ]
    },
    {
      "paperId": "5d2d50e2adc54af98ed556b7facca591fda14863",
      "title": "Molecular evolution of Drosophila Sex-lethal and related sex determining genes",
      "year": 2012,
      "citationCount": 16,
      "authors": [
        {
          "authorId": "5170179",
          "name": "Charles Mullon"
        },
        {
          "authorId": "3037434",
          "name": "A. Pomiankowski"
        },
        {
          "authorId": "32020255",
          "name": "M. Reuter"
        }
      ]
    },
    {
      "paperId": "5f2c59eaaf4a5fd47a3830802e1f4d9c9c4f50bc",
      "title": "A male-killing Wolbachia carries a feminizing factor and is associated with degradation of the sex-determining system of its host",
      "year": 2012,
      "citationCount": 60,
      "authors": [
        {
          "authorId": "2070453896",
          "name": "Takafumi N. Sugimoto"
        },
        {
          "authorId": "50648123",
          "name": "Y. Ishikawa"
        }
      ]
    }
  ],
  "references": [
    {
      "paperId": "c56421643f60b8c32ce783d999c3ba412a2bbeb5",
      "title": "Solution structure of FKBP, a rotamase enzyme and receptor for FK506 and rapamycin",
      "year": 1991,
      "citationCount": 268,
      "authors": [
        {
          "authorId": "6485491",
          "name": "S. Michnick"
        },
        {
          "authorId": "47825433",
          "name": "M. Rosen"
        },
        {
          "authorId": "6606749",
          "name": "T. Wandless"
        },
        {
          "authorId": "1802151",
          "name": "M. Karplus"
        },
        {
          "authorId": "2610390",
          "name": "S. Schreiber"
        }
      ]
    },
    {
      "paperId": "ad75a86e49343561c64151300882f4a2966d8931",
      "title": "Binding of the Drosophila Sex-lethal gene product to the alternative splice site of transformer primary transcript",
      "year": 1990,
      "citationCount": 298,
      "authors": [
        {
          "authorId": "39741295",
          "name": "Kunio Inoue"
        },
        {
          "authorId": "4490827",
          "name": "K. Hoshijima"
        },
        {
          "authorId": "153005057",
          "name": "H. Sakamoto"
        },
        {
          "authorId": "5092719",
          "name": "Y. Shimura"
        }
      ]
    },
    {
      "paperId": "a725ee7efe89147e75fab630b66421a4138cdbb4",
      "title": "Sex in flies: the splice of life",
      "year": 1989,
      "citationCount": 459,
      "authors": [
        {
          "authorId": "3231773",
          "name": "B. S. Baker"
        }
      ]
    },
    {
      "paperId": "dc99bacb3d19c902951feef3596f4142c4a1c89f",
      "title": "Sex-specific alternative splicing of RNA from the transformer gene results from sequence-dependent splice site blockage",
      "year": 1989,
      "citationCount": 272,
      "authors": [
        {
          "authorId": "5636467",
          "name": "B. Sosnowski"
        },
        {
          "authorId": "5428023",
          "name": "J. M. Belote"
        },
        {
          "authorId": "1880088",
          "name": "M. Mckeown"
        }
      ]
    },
    {
      "paperId": "402d5661845c117a7dc82cb01dcf8cc37fc60d5b",
      "title": "A common RNA recognition motif identified within a defined U1 RNA binding domain of the 70K U1 snRNP protein",
      "year": 1989,
      "citationCount": 494,
      "authors": [
        {
          "authorId": "4438120",
          "name": "C. Query"
        },
        {
          "authorId": "153012674",
          "name": "R. Bentley"
        },
        {
          "authorId": "2123582",
          "name": "J. Keene"
        }
      ]
    },
    {
      "paperId": "841c2d3d0c5a6c9e6ec945cb89ed0a01caace997",
      "title": "A binding consensus: RNA-protein interactions in splicing, snRNPs, and sex",
      "year": 1989,
      "citationCount": 124,
      "authors": [
        {
          "authorId": "7018634",
          "name": "I. Mattaj"
        }
      ]
    },
    {
      "paperId": "3a4b87accc5ee6a523237246f16c998bef67c0bf",
      "title": "The sex determination locus transformer-2 of Drosophila encodes a polypeptide with similarity to RNA binding proteins",
      "year": 1989,
      "citationCount": 146,
      "authors": [
        {
          "authorId": "3569092",
          "name": "T. Goralski"
        },
        {
          "authorId": "143708366",
          "name": "J. Edström"
        },
        {
          "authorId": "3231773",
          "name": "B. S. Baker"
        }
      ]
    },
    {
      "paperId": "1fa9d6e1e83dd1bf461f748ecedcb412dfdeccec",
      "title": "Drosophila doublesex gene controls somatic sexual differentiation by producing alternatively spliced mRNAs encoding related sex-specific polypeptides",
      "year": 1989,
      "citationCount": 662,
      "authors": [
        {
          "authorId": "4656860",
          "name": "K. C. Burtis"
        },
        {
          "authorId": "3231773",
          "name": "B. S. Baker"
        }
      ]
    },
    {
      "paperId": "a763bd522d51b375e3ee65f373fb4e8c16218494",
      "title": "The sex-determining gene tra-2 of Drosophila encodes a putative RNA binding protein",
      "year": 1988,
      "citationCount": 228,
      "authors": [
        {
          "authorId": "4760876",
          "name": "H. Amrein"
        },
        {
          "authorId": "2060742930",
          "name": "M. Gorman"
        },
        {
          "authorId": "3596225",
          "name": "R. Nöthiger"
        }
      ]
    },
    {
      "paperId": "31c41292c41bcf84bb56b5e747a4b2939d59e51b",
      "title": "Ectopic expression of the female transformer gene product leads to female differentiation of chromosomally male drosophila",
      "year": 1988,
      "citationCount": 163,
      "authors": [
        {
          "authorId": "1880088",
          "name": "M. Mckeown"
        },
        {
          "authorId": "5428023",
          "name": "J. M. Belote"
        },
        {
          "authorId": "52198488",
          "name": "R. T. Boggs"
        }
      ]
    },
    {
      "paperId": "580f5239f8b7cc690904cae8d4d7e67ad885f774",
      "title": "The control of alternative splicing at genes regulating sexual differentiation in D. melanogaster",
      "year": 1988,
      "citationCount": 273,
      "authors": [
        {
          "authorId": "13490960",
          "name": "R. Nagoshi"
        },
        {
          "authorId": "1880088",
          "name": "M. Mckeown"
        },
        {
          "authorId": "4656860",
          "name": "K. C. Burtis"
        },
        {
          "authorId": "5428023",
          "name": "J. M. Belote"
        },
        {
          "authorId": "3231773",
          "name": "B. S. Baker"
        }
      ]
    },
    {
      "paperId": "5f16e08ddfc0bd048584f3bb67870791bcf95b08",
      "title": "A molecular analysis of doublesex, a bifunctional gene that controls both male and female sexual differentiation in Drosophila melanogaster.",
      "year": 1988,
      "citationCount": 166,
      "authors": [
        {
          "authorId": "3231773",
          "name": "B. S. Baker"
        },
        {
          "authorId": "9013567",
          "name": "M. Wolfner"
        }
      ]
    },
    {
      "paperId": "9b2b99187e428a3c9c998987d6c6949ac2ec9928",
      "title": "The dual functions of a sex determination gene in Drosophila melanogaster.",
      "year": 1983,
      "citationCount": 59,
      "authors": [
        {
          "authorId": "5428023",
          "name": "J. M. Belote"
        },
        {
          "authorId": "3231773",
          "name": "B. S. Baker"
        }
      ]
    },
    {
      "paperId": "9243751217533163b19f7442e85fc50f8ac4bb96",
      "title": "Sex determination in Drosophila melanogaster: analysis of transformer-2, a sex-transforming locus.",
      "year": 1982,
      "citationCount": 116,
      "authors": [
        {
          "authorId": "5428023",
          "name": "J. M. Belote"
        },
        {
          "authorId": "2251031562",
          "name": "Bruce S. Baker"
        }
      ]
    },
    {
      "paperId": "ce8c1a1c50a85a52580a9d7fcb9d9e67693b8ba7",
      "title": "Sex and the single cell. I. On the action of major loci affecting sex determination in Drosophila melanogaster.",
      "year": 1980,
      "citationCount": 352,
      "authors": [
        {
          "authorId": "3231773",
          "name": "B. S. Baker"
        },
        {
          "authorId": "48041553",
          "name": "K. Ridge"
        }
      ]
    },
    {
      "paperId": "340191a81fac67f3ea08debb38e840cbaa107a40",
      "title": "Regulation of sex-specific RNA splicing at the Drosophila doublesex gene: cis-acting mutations in exon sequences alter sex-specific RNA splicing patterns.",
      "year": 1990,
      "citationCount": 158,
      "authors": [
        {
          "authorId": "13490960",
          "name": "R. Nagoshi"
        },
        {
          "authorId": "3231773",
          "name": "B. S. Baker"
        }
      ]
    },
    {
      "paperId": "1d77063771065a77df8f3a699ed35d788ed76452",
      "title": "Molecular genetics of transformer, a genetic switch controlling sexual differentiation in Drosophila.",
      "year": 1989,
      "citationCount": 51,
      "authors": [
        {
          "authorId": "5428023",
          "name": "J. M. Belote"
        },
        {
          "authorId": "1880088",
          "name": "M. Mckeown"
        },
        {
          "authorId": "52198488",
          "name": "R. T. Boggs"
        },
        {
          "authorId": "38058393",
          "name": "R. Ohkawa"
        },
        {
          "authorId": "5636467",
          "name": "B. Sosnowski"
        }
      ]
    },
    {
      "paperId": "d8045239e4507bf17d284f706c6ccf61ed2517a3",
      "title": "Pre-mRNA splicing.",
      "year": 1986,
      "citationCount": 319,
      "authors": [
        {
          "authorId": "2116272796",
          "name": "M. Green"
        }
      ]
    },
    {
      "paperId": "b7aa796a361131ef72aabc4e79a2ba9e97324ef4",
      "title": "Sex determination in Drosophila",
      "year": 1985,
      "citationCount": 64,
      "authors": [
        {
          "authorId": "3596225",
          "name": "R. Nöthiger"
        },
        {
          "authorId": "1435749268",
          "name": "M. Steinmann‐Zwicky"
        }
      ]
    },
    {
      "paperId": "0f252c64ba2cd850f239a035fe9e317d63bd6d0f",
      "title": "Oligonucleotide-directed mutagenesis of DNA fragments cloned into M13 vectors.",
      "year": 1983,
      "citationCount": 765,
      "authors": [
        {
          "authorId": "3529813",
          "name": "M. Zoller"
        },
        {
          "authorId": "48533786",
          "name": "M. Smith"
        }
      ]
    },
    {
      "paperId": "643665a98823cb368ce36196b22d233553246613",
      "title": "Autosomal mutations that interfere with sex determination in somatic cells of Drosophila have no direct effect on the germline.",
      "year": 1982,
      "citationCount": 123,
      "authors": [
        {
          "authorId": "2241443102",
          "name": "Trudi Schüpbach"
        }
      ]
    },
    {
      "paperId": null,
      "title": "McKeown for tra cDNA and H. Amrein for tra-2 cDNA. Supported by Grant-in-Aid 62065009 for specially promoted research from the Ministry of Education",
      "year": null,
      "citationCount": null,
      "authors": []
    },
    {
      "paperId": null,
      "title": "Adaptational biodegradation is indicated by an acceleration in microbiological destruction of chemicals after their introduction into a given environment (3, 4)",
      "year": null,
      "citationCount": null,
      "authors": []
    },
    {
      "paperId": null,
      "title": "Pre-mRNA expressed from the deletion construct of copia-dtz was spliced at the fitz acceptor site even in the presence of the tra and tra-2 products in Kc cells",
      "year": null,
      "citationCount": null,
      "authors": []
    }
  ]
}